{"Exif":{"Lat":47.093796688333335,"Long":12.169565293888889,"Date":"2015-08-27T10:49:16+02:00","Tags":{"ApertureValue":3.2943640690702924,"ComponentsConfiguration":"1 2 3 0","CompressedBitsPerPixel|*imagemeta.rat[uint32]":"159/100","Copyright":"COPYRIGHT,2011","CreateDate":"2015:08:27 10:49:16","DateTimeOriginal":"2015:08:27 10:49:16","DigitalZoomRatio|*imagemeta.rat[uint32]":"0","ExposureCompensation|*imagemeta.rat[int32]":"0","ExposureIndex|*imagemeta.rat[uint32]":"1","ExposureTime|*imagemeta.rat[uint32]":"1/850","FNumber|*imagemeta.rat[uint32]":"33/10","FileSource|uint8":"3","FocalLengthIn35mmFormat|uint16":"28","FocalLength|*imagemeta.rat[uint32]":"41/10","ISO|uint16":"80","LightSource|uint16":"0","Make":"SAMSUNG","MaxApertureValue":3.2943640690702924,"Model":"SAMSUNG ST30","ModifyDate":"2015:08:27 10:49:19","Orientation|uint16":"1","RelatedSoundFile":"RelatedSound","SceneCaptureType|uint16":"0","SceneType|uint8":"1","ShutterSpeedValue":0.0011775467067292578,"Software":"F/W VER 3.2000","YCbCrPositioning|uint16":"2"}}}
